ulmo/__init__.py
ulmo/cdec/__init__.py
ulmo/cdec/historical/__init__.py
ulmo/cdec/historical/core.py
ulmo/cpc/__init__.py
ulmo/cpc/drought/__init__.py
ulmo/cpc/drought/core.py
ulmo/cuahsi/__init__.py
ulmo/cuahsi/his_central/__init__.py
ulmo/cuahsi/his_central/core.py
ulmo/cuahsi/wof/__init__.py
ulmo/cuahsi/wof/core.py
ulmo/lcra/__init__.py
ulmo/lcra/hydromet/__init__.py
ulmo/lcra/hydromet/core.py
ulmo/lcra/waterquality/__init__.py
ulmo/lcra/waterquality/core.py
ulmo/nasa/__init__.py
ulmo/nasa/daymet/__init__.py
ulmo/nasa/daymet/core.py
ulmo/ncdc/__init__.py
ulmo/ncdc/cirs/__init__.py
ulmo/ncdc/cirs/core.py
ulmo/ncdc/ghcn_daily/__init__.py
ulmo/ncdc/ghcn_daily/core.py
ulmo/ncdc/gsod/__init__.py
ulmo/ncdc/gsod/core.py
ulmo/ncdc/gsod/pytables.py
ulmo/noaa/__init__.py
ulmo/noaa/goes/__init__.py
ulmo/noaa/goes/core.py
ulmo/noaa/goes/parsers.py
ulmo/twc/__init__.py
ulmo/twc/kbdi/__init__.py
ulmo/twc/kbdi/core.py
ulmo/usace/__init__.py
ulmo/usace/rivergages/__init__.py
ulmo/usace/rivergages/core.py
ulmo/usace/swtwc/__init__.py
ulmo/usace/swtwc/core.py
ulmo/usgs/__init__.py
ulmo/usgs/eddn/__init__.py
ulmo/usgs/eddn/core.py
ulmo/usgs/eddn/parsers.py
ulmo/usgs/ned/__init__.py
ulmo/usgs/ned/core.py
ulmo/usgs/nwis/__init__.py
ulmo/usgs/nwis/core.py
ulmo/usgs/nwis/hdf5.py
ulmo/util/__init__.py
ulmo/util/misc.py
ulmo/util/pytables.py
ulmo/util/raster.py
ulmo/waterml/__init__.py
ulmo/waterml/common.py
ulmo/waterml/v1_0.py
ulmo/waterml/v1_1.py
ulmo-0.8.8.dist-info/AUTHORS
ulmo-0.8.8.dist-info/LICENSE
ulmo-0.8.8.dist-info/METADATA
ulmo-0.8.8.dist-info/WHEEL
ulmo-0.8.8.dist-info/top_level.txt
ulmo-0.8.8.dist-info/RECORD
