Metadata-Version: 2.1
Name: ulmo
Version: 0.8.8
Summary: clean, simple and fast access to public hydrology and climatology data
Home-page: https://github.com/ulmo-dev/ulmo/
Author: Dharhas Pothina
Author-email: dharhas@gmail.com
License: BSD
Keywords: his ulmo water waterml cuahsi wateroneflow usgs ned
Platform: any
Classifier: Development Status :: 4 - Beta
Classifier: Intended Audience :: Science/Research
Classifier: License :: OSI Approved :: BSD License
Classifier: Operating System :: OS Independent
Classifier: Programming Language :: Python
Classifier: Programming Language :: Python :: 2
Classifier: Programming Language :: Python :: 2.7
Classifier: Programming Language :: Python :: 3
Classifier: Programming Language :: Python :: 3.5
Classifier: Programming Language :: Python :: 3.6
Classifier: Programming Language :: Python :: 3.7
Classifier: Programming Language :: Python :: 3.8
Classifier: Programming Language :: Python :: 3.9
Classifier: Topic :: Software Development :: Libraries :: Python Modules
License-File: LICENSE
License-File: AUTHORS
Requires-Dist: appdirs
Requires-Dist: beautifulsoup4
Requires-Dist: future
Requires-Dist: geojson
Requires-Dist: isodate
Requires-Dist: lxml
Requires-Dist: numpy
Requires-Dist: pandas
Requires-Dist: python-dateutil
Requires-Dist: requests
Requires-Dist: suds-jurko
